linkplay/__init__.py
linkplay/__main__.py
linkplay/__version__.py
linkplay/bridge.py
linkplay/consts.py
linkplay/controller.py
linkplay/discovery.py
linkplay/endpoint.py
linkplay/exceptions.py
linkplay/manufacturers.py
linkplay/utils.py
python_linkplay-0.2.13.dist-info/licenses/LICENSE
python_linkplay-0.2.13.dist-info/METADATA
python_linkplay-0.2.13.dist-info/WHEEL
python_linkplay-0.2.13.dist-info/top_level.txt
python_linkplay-0.2.13.dist-info/RECORD
