Metadata-Version: 2.4
Name: python_linkplay
Version: 0.2.13
Summary: A Python Library for Seamless LinkPlay Device Control
Author: Velleman Group nv
License: MIT
Classifier: Programming Language :: Python :: 3
Requires-Python: >=3.11
License-File: LICENSE
Requires-Dist: async-timeout>=4.0.3
Requires-Dist: aiohttp>=3.8.5
Requires-Dist: appdirs>=1.4.4
Requires-Dist: async_upnp_client>=0.36.2
Requires-Dist: deprecated>=1.2.14
Requires-Dist: aiofiles>=23.1.0
Provides-Extra: testing
Requires-Dist: pytest>=7.3.1; extra == "testing"
Requires-Dist: pytest-cov>=4.1.0; extra == "testing"
Requires-Dist: pytest-mock>=3.10.0; extra == "testing"
Requires-Dist: pytest-asyncio>=0.23.3; extra == "testing"
Requires-Dist: mypy>=1.3.0; extra == "testing"
Requires-Dist: ruff>=0.5.4; extra == "testing"
Requires-Dist: tox>=4.6.0; extra == "testing"
Requires-Dist: typing-extensions>=4.6.3; extra == "testing"
Requires-Dist: pre-commit>=3.8.0; extra == "testing"
Dynamic: license-file
